bdtdecimaltowordsconverter/__init__.py
bdtdecimaltowordsconverter/bdtdecimaltowordsconverter.py
bdtdecimaltowordsconverter-1.0.0.dist-info/METADATA
bdtdecimaltowordsconverter-1.0.0.dist-info/RECORD
bdtdecimaltowordsconverter-1.0.0.dist-info/WHEEL
bdtdecimaltowordsconverter-1.0.0.dist-info/top_level.txt
