Metadata-Version: 2.1
Name: bdtdecimaltowordsconverter
Version: 1.0.0
Summary: bdtdecimaltowordsconverter is created for converting decimal to word in both bangla and english in BDT format
Home-page: https://github.com/mahfuzcmt/BanglaDecimalToWordConverter
Author: Mahfuz Ahmed
Author-email: mahfuzcmt@gmail.com
License: UNKNOWN
Platform: UNKNOWN
Classifier: Programming Language :: Python :: 3
Classifier: License :: OSI Approved :: MIT License
Classifier: Operating System :: OS Independent
